LICENSE
README.md
setup.py
bin/pymasync
pymacaron_async/__init__.py
pymacaron_async/app.py
pymacaron_async/cmd.py
pymacaron_async/loader.py
pymacaron_async/serialization.py
pymacaron_async.egg-info/PKG-INFO
pymacaron_async.egg-info/SOURCES.txt
pymacaron_async.egg-info/dependency_links.txt
pymacaron_async.egg-info/not-zip-safe
pymacaron_async.egg-info/requires.txt
pymacaron_async.egg-info/top_level.txt
test/test_pep8.py
test/test_serialize.py