Metadata-Version: 2.1
Name: pymacaron-async
Version: 2.0.100
Summary: Seamless asynchronous execution of method calls inside a PyMacaron endpoint, using celery+redis
Home-page: https://github.com/pymacaron/pymacaron-async
Author: Erwan Lemonnier
Author-email: erwan@lemonnier.se
License: BSD
Platform: any
Classifier: Environment :: Web Environment
Classifier: Intended Audience :: Developers
Classifier: License :: OSI Approved :: BSD License
Classifier: Operating System :: OS Independent
Classifier: Programming Language :: Python
Classifier: Topic :: Internet :: WWW/HTTP :: Dynamic Content
Classifier: Topic :: Software Development :: Libraries :: Python Modules
License-File: LICENSE
